{
  "id": 7,
  "name": "프로비스타 호텔 강남",
  "grade": 4,
  "discount": 30,
  "check_in_date": 1466046000000,
  "check_out_date": 1466164800000,
  "guest_count": 1,
  "rate": 4,
  "review_count": 989,
  "service": [
    "internet",
    "breakfast",
    "dining",
    "gym",
    "business_center"
  ],
  "address_1": "1677-8, Seocho1-dong, Seocho-gu",
  "address_2": "",
  "phone" : "02-555-1234",
  "desc": "서울의 최고 위치에 있는 프로비스타 호텔 강남에서 도시의 모든 것을 맛볼 수 있습니다. 비즈니스 여행객과 관광객 모두 호텔의 시설과 서비스를 즐길 수 있습니다. 호텔의 Wi-Fi (무료/전 객실), 일일 청소 서비스, 우편 서비스, 24시간 프런트 데스크, 익스프레스 체크인/체크아웃 등을 활용할 수 있습니다. 각 객실은 우아하게 꾸며져 있으며 편리한 시설을 갖추고 있습니다. 호텔은 다양한 레크리에이션 기회를 제공합니다. 편리함과 편안함을 제공하는 프로비스타 호텔 강남에서 머문다면 서울에 있는 동안 탁월한 선택이 될 것입니다.",
  "latitude": 37.494881999999997,
  "longitude": 127.018596,
  "dining": "유럽식 아침 식사가 제공되며 별도 요금이 적용됩니다.",
  "rooms_desc": "각각 다르게 가구가 비치된 160개의 객실 모두 무료 WiFi 및 룸서비스 등을 갖추고 있습니다. 또한, 좌석 공간, 케이블 TV 및 냉장고도 이용하실 수 있습니다.",
  "property": "이 호텔에는 레스토랑 외에 헬스클럽 및 바/라운지도 있습니다. 공용 장소에서의 WiFi의 경우 무료입니다. 기타 편의 시설로는 커피숍/카페, 비즈니스 센터, 드라이클리닝 서비스 등이 있습니다.",
  "highlight": "",
  "amenities": "",
  "policies": "애완동물을 동반하실 수 없습니다.",
  "pictures": [
    {
      "image_url": "http://slothstay.com/resources/image/7/main.jpg",
      "desc": "대표사진"
    },
    {
      "image_url": "http://slothstay.com/resources/image/7/1.jpg",
      "desc": "객실"
    },
    {
      "image_url": "http://slothstay.com/resources/image/7/1.jpg",
      "desc": "객실"
    },
    {
      "image_url": "http://slothstay.com/resources/image/7/1.jpg",
      "desc": "욕실"
    }
],
  "rooms": [
    {
      "name": "스탠다드 더블룸",
      "price": "85365",
      "etc": [
        "예약무료 취소",
        "무료 주차",
        "무료 인터넷"
      ],
      "detail": "2인기준/최대3인/조식불포함, 31제곱미터(더블침대 1개)",
      "image_url": "http://slothstay.com/resources/image/7/4.jpg",
      "check_in_early": 4,
      "check_in_late": 4,
      "check_out_early": 4,
      "check_out_late": 4
    },
{
      "name": "스탠다드 더블룸",
      "price": "85365",
      "etc": [
        "예약무료 취소",
        "무료 주차",
        "무료 인터넷"
      ],
      "detail": "2인기준/최대3인/조식불포함, 31제곱미터(더블침대 1개)",
      "image_url": "http://slothstay.com/resources/image/7/4.jpg",
      "check_in_early": 4,
      "check_in_late": 4,
      "check_out_early": 4,
      "check_out_late": 4
    }
]
}
